proj/CODE/UART/UART_synth.sv
/* Generated by Yosys 0.9 (git sha1 1979e0b) */

module UART_synth(i_clk, i_Tx_DV, i_Tx_b, i_enable, i_select, o_Tx_active, o_Tx_serial, o_data_sent, o_ready, o_data_recieved);
  wire [2:0] _000_;
  wire _001_;
  wire _002_;
  wire _003_;
  wire _004_;
  wire _005_;
  wire [7:0] _006_;
  wire [2:0] _007_;
  wire _008_;
  wire _009_;
  wire _010_;
  wire _011_;
  wire _012_;
  wire _013_;
  wire _014_;
  wire _015_;
  wire _016_;
  wire _017_;
  wire _018_;
  wire _019_;
  wire _020_;
  wire _021_;
  wire _022_;
  wire _023_;
  wire _024_;
  wire _025_;
  wire _026_;
  wire _027_;
  wire _028_;
  wire _029_;
  wire _030_;
  wire _031_;
  wire _032_;
  wire _033_;
  wire _034_;
  wire _035_;
  wire _036_;
  wire _037_;
  wire _038_;
  wire _039_;
  wire _040_;
  wire _041_;
  wire _042_;
  wire _043_;
  wire _044_;
  wire _045_;
  wire _046_;
  wire _047_;
  wire _048_;
  wire _049_;
  wire _050_;
  wire _051_;
  wire _052_;
  wire _053_;
  wire _054_;
  wire _055_;
  wire _056_;
  wire _057_;
  wire _058_;
  wire _059_;
  wire _060_;
  wire _061_;
  wire _062_;
  wire _063_;
  wire _064_;
  wire _065_;
  wire _066_;
  wire _067_;
  wire _068_;
  wire _069_;
  wire _070_;
  wire _071_;
  wire _072_;
  wire _073_;
  wire _074_;
  wire _075_;
  wire _076_;
  wire _077_;
  wire _078_;
  wire _079_;
  wire _080_;
  wire _081_;
  wire _082_;
  wire _083_;
  wire _084_;
  wire _085_;
  wire _086_;
  wire _087_;
  wire _088_;
  wire _089_;
  wire _090_;
  wire _091_;
  wire _092_;
  wire _093_;
  wire _094_;
  reg [2:0] curr_state = 3'h0;
  input i_Tx_DV;
  input [7:0] i_Tx_b;
  input i_clk;
  input i_enable;
  input i_select;
  output o_Tx_active;
  reg o_Tx_active;
  output o_Tx_serial;
  reg o_Tx_serial;
  output o_data_recieved;
  reg o_data_recieved;
  output o_data_sent;
  reg o_data_sent;
  output o_ready;
  reg o_ready;
  reg [7:0] r_Tx_data = 8'h00;
  reg [2:0] r_bit_index = 3'h0;
  wire [7:0] r_clock_count;
  assign _048_ = ~i_Tx_DV;
  assign _049_ = ~curr_state[1];
  assign _050_ = ~curr_state[0];
  assign _051_ = ~curr_state[2];
  assign _052_ = ~r_bit_index[2];
  assign _053_ = ~r_bit_index[1];
  assign _054_ = ~r_bit_index[0];
  assign _055_ = _049_ & _050_;
  assign _056_ = curr_state[1] | curr_state[0];
  assign _057_ = i_Tx_DV & _051_;
  assign _058_ = _048_ | _056_;
  assign _059_ = _055_ & _057_;
  assign _060_ = curr_state[2] | _058_;
  assign _061_ = o_ready | _055_;
  assign _005_ = _060_ & _061_;
  assign _062_ = curr_state[1] & _051_;
  assign _000_[2] = curr_state[0] & _062_;
  assign _063_ = ~_000_[2];
  assign _064_ = o_data_sent & _056_;
  assign _004_ = _000_[2] | _064_;
  assign _065_ = _050_ & _062_;
  assign _066_ = ~_065_;
  assign _067_ = r_Tx_data[0] | r_bit_index[2];
  assign _068_ = r_Tx_data[4] | _052_;
  assign _069_ = _067_ & _068_;
  assign _070_ = r_bit_index[1] | _069_;
  assign _071_ = i_select & i_enable;
  assign _072_ = ~_071_;
  assign _073_ = _054_ & _071_;
  assign _074_ = _052_ & r_bit_index[1];
  assign _075_ = _052_ | r_Tx_data[6];
  assign _076_ = r_bit_index[2] | r_Tx_data[2];
  assign _077_ = _075_ & _076_;
  assign _078_ = _053_ | _077_;
  assign _079_ = _073_ & _078_;
  assign _080_ = _070_ & _079_;
  assign _081_ = r_bit_index[2] | r_Tx_data[1];
  assign _082_ = _052_ | r_Tx_data[5];
  assign _083_ = _081_ & _082_;
  assign _084_ = r_bit_index[0] & _071_;
  assign _085_ = r_bit_index[2] | r_Tx_data[3];
  assign _086_ = _052_ | r_Tx_data[7];
  assign _087_ = r_bit_index[1] & _086_;
  assign _088_ = _085_ & _087_;
  assign _089_ = _053_ & _083_;
  assign _090_ = _088_ | _089_;
  assign _091_ = _084_ & _090_;
  assign _092_ = _080_ | _091_;
  assign _093_ = _065_ & _092_;
  assign _094_ = _051_ & _071_;
  assign _008_ = curr_state[2] | _072_;
  assign _009_ = o_Tx_serial & _008_;
  assign _010_ = _055_ | _000_[2];
  assign _011_ = _009_ | _010_;
  assign _012_ = _049_ & curr_state[0];
  assign _002_ = _093_ | _011_;
  assign _013_ = o_Tx_active | _059_;
  assign _001_ = _063_ & _013_;
  assign _014_ = i_Tx_b[0] & _059_;
  assign _015_ = r_Tx_data[0] & _060_;
  assign _006_[0] = _014_ | _015_;
  assign _016_ = i_Tx_b[1] & _059_;
  assign _017_ = r_Tx_data[1] & _060_;
  assign _006_[1] = _016_ | _017_;
  assign _018_ = i_Tx_b[2] & _059_;
  assign _019_ = r_Tx_data[2] & _060_;
  assign _006_[2] = _018_ | _019_;
  assign _020_ = i_Tx_b[3] & _059_;
  assign _021_ = r_Tx_data[3] & _060_;
  assign _006_[3] = _020_ | _021_;
  assign _022_ = i_Tx_b[4] & _059_;
  assign _023_ = r_Tx_data[4] & _060_;
  assign _006_[4] = _022_ | _023_;
  assign _024_ = i_Tx_b[5] & _059_;
  assign _025_ = r_Tx_data[5] & _060_;
  assign _006_[5] = _024_ | _025_;
  assign _026_ = i_Tx_b[6] & _059_;
  assign _027_ = r_Tx_data[6] & _060_;
  assign _006_[6] = _026_ | _027_;
  assign _028_ = i_Tx_b[7] & _059_;
  assign _029_ = r_Tx_data[7] & _060_;
  assign _006_[7] = _028_ | _029_;
  assign _030_ = _056_ & _066_;
  assign _031_ = r_bit_index[0] & _030_;
  assign _032_ = r_bit_index[0] ^ _071_;
  assign _033_ = _065_ & _032_;
  assign _007_[0] = _031_ | _033_;
  assign _034_ = r_bit_index[1] & _084_;
  assign _035_ = ~_034_;
  assign _036_ = _065_ & _035_;
  assign _037_ = _030_ | _036_;
  assign _038_ = _065_ & _084_;
  assign _039_ = r_bit_index[1] | _038_;
  assign _007_[1] = _037_ & _039_;
  assign _040_ = r_bit_index[2] & _037_;
  assign _041_ = _074_ & _038_;
  assign _007_[2] = _040_ | _041_;
  assign _042_ = r_bit_index[1] & r_bit_index[0];
  assign _043_ = r_bit_index[2] & _042_;
  assign _044_ = _072_ | _043_;
  assign _045_ = _065_ & _044_;
  assign _000_[0] = _059_ | _045_;
  assign _046_ = _094_ & _012_;
  assign _000_[1] = _065_ | _046_;
  assign _047_ = o_data_recieved & _056_;
  assign _003_ = _059_ | _047_;
  always @(posedge i_clk)
      o_Tx_active <= _001_;
  always @(posedge i_clk)
      o_Tx_serial <= _002_;
  always @(posedge i_clk)
      o_data_sent <= _004_;
  always @(posedge i_clk)
      o_ready <= _005_;
  always @(posedge i_clk)
      o_data_recieved <= _003_;
  always @(posedge i_clk)
      curr_state[0] <= _000_[0];
  always @(posedge i_clk)
      curr_state[1] <= _000_[1];
  always @(posedge i_clk)
      curr_state[2] <= _000_[2];
  always @(posedge i_clk)
      r_bit_index[0] <= _007_[0];
  always @(posedge i_clk)
      r_bit_index[1] <= _007_[1];
  always @(posedge i_clk)
      r_bit_index[2] <= _007_[2];
  always @(posedge i_clk)
      r_Tx_data[0] <= _006_[0];
  always @(posedge i_clk)
      r_Tx_data[1] <= _006_[1];
  always @(posedge i_clk)
      r_Tx_data[2] <= _006_[2];
  always @(posedge i_clk)
      r_Tx_data[3] <= _006_[3];
  always @(posedge i_clk)
      r_Tx_data[4] <= _006_[4];
  always @(posedge i_clk)
      r_Tx_data[5] <= _006_[5];
  always @(posedge i_clk)
      r_Tx_data[6] <= _006_[6];
  always @(posedge i_clk)
      r_Tx_data[7] <= _006_[7];
endmodule

proj/CODE/UART/UART_def.vh
`ifndef UART_DEF

`define UART_DEF

`define IDLE 3'b000
`define START 3'b001
`define DATA_BITS 3'b010
`define STOP 3'b011
`define CLEAN 3'b100

`endif

proj/CODE/UART/UART.sv
`include "UART_def.vh"

module UART (i_clk, i_Tx_DV, i_Tx_b, i_enable, i_select, o_Tx_active, o_Tx_serial, o_data_sent, o_ready, o_data_recieved);

parameter CLKS_PER_BIT = 1;
parameter m = 8;

input  logic i_clk;
input  logic i_Tx_DV;
input  logic [m-1:0] i_Tx_b;
input  logic i_enable;
input  logic i_select;
output logic o_Tx_active;
output logic o_Tx_serial;
output logic o_data_sent;
output logic o_ready;
output logic o_data_recieved;

/*Zmienne wewnętrznych rejestrów modułu*/
reg [2:0] curr_state = 0;
reg [7:0] r_clock_count = 0;
reg [2:0] r_bit_index = 0;
reg [m-1:0] r_Tx_data = 0;
   
/*Układ synchroniczny aktywowany wzrastającym zboczem zegarowym*/
always @(posedge i_clk) begin

    /*Sprawdzamy obecny stan automatu*/
    case (curr_state)
    
    /*Stan bezczynności*/
    `IDLE: begin
    
        /*Ustawienie domyślnych wartości wyjść*/
        o_Tx_serial <= 1'b1;
        o_ready <= 1'b1;
        o_data_recieved <= 1'b0;
        o_data_sent <= 1'b0;
        r_clock_count <= 0;
        r_bit_index <= 0;
         
        /*Sprawdź czy należy rozpocząć transmisje danych*/
        if (i_Tx_DV == 1'b1) begin
        
            /*Uaktualnij sygnały wyjściowe*/
            o_ready <= 1'b0;
            o_data_recieved <= 1'b1;
            o_Tx_active <= 1'b1;
            r_Tx_data <= i_Tx_b;
            
            /*Przejdź do następnego stanu automatu*/
            curr_state <= `START;
        end
        
        /*W przeciwnym wypadku - pozostań w tym samym stanie*/
        else begin
        	curr_state <= `IDLE;
       	end
    end
     
    /*Stan rozpoczęcia przesyłu danych*/
    `START: begin
    
        /*Sprawdź warunki konieczne do kontynuowania transmisji*/
        if (&{i_select, i_enable}) begin
        
            /*Rozpoczęcie transmisji danych*/
            o_Tx_serial <= 1'b0;
            
            /*Zmiana stanu automatu w zależności od momentu cyklu*/
            if (r_clock_count < CLKS_PER_BIT - 1) begin
                r_clock_count <= r_clock_count + 1;
                curr_state <= `START;
            end
            else begin
                r_clock_count <= 0;
                curr_state <= `DATA_BITS;
            end
        end
        
        /*Jeżeli warunki nie są spełnione - następuje powrót do stanu bezczynności*/
        else begin
        	curr_state <= `IDLE;
        end
    end

    /*Stan przesyłania danych*/
    `DATA_BITS: begin
    
        /*Sprawdź warunki konieczne do kontynuowania transmisji*/
        if (&{i_select, i_enable}) begin
        
            /*Wystawienie następnego bitu na wyjście*/
            o_Tx_serial <= r_Tx_data[r_bit_index];
            
            /*Zmiana stanu automatu w zależności od momentu cyklu*/
            if (r_clock_count < CLKS_PER_BIT - 1) begin
                r_clock_count <= r_clock_count + 1;
                curr_state <= `DATA_BITS;
            end
            else begin
                /*Reset cyklu*/
                r_clock_count <= 0;

                if (r_bit_index < 7) begin
                    r_bit_index <= r_bit_index + 1;
                    curr_state <= `DATA_BITS;
                end
                else begin
                    r_bit_index <= 0;
                    curr_state <= `STOP;
                end
            end
        end
        
        /*Jeżeli warunki nie są spełnione - następuje powrót do stanu bezczynności*/
        else begin
        	curr_state <= `STOP;
       	end
    end
      
    /*Stan zatrzymania transmisji*/
    `STOP: begin
    
        /*Zakończenie transmisji danych*/
        o_Tx_serial <= 1'b1;
        
        /*Zmiana stanu automatu w zależności od momentu cyklu*/
        if (r_clock_count < CLKS_PER_BIT - 1) begin
            r_clock_count <= r_clock_count + 1;
            curr_state <= `STOP;
        end
        else begin
            o_data_sent <= 1'b1;
            r_clock_count <= 0;
            curr_state <= `CLEAN;
            o_Tx_active <= 1'b0;
        end
    end  
       
    /*Stan "Sprzątania" - powrót wszystkich wyjśc i rejestrów do wartości domyślnych + przejście do stanu bezczynności*/
    `CLEAN: begin
        o_Tx_serial <= 1'b1;
        o_ready <= 1'b1;
        o_data_recieved <= 1'b0;
        o_data_sent <= 1'b0;
        r_clock_count <= 0;
        r_bit_index <= 0;
        curr_state <= `IDLE;
    end
       
    /*Stan domyślny, to przejście do stanu bezczynności*/
    default: curr_state <= `IDLE;

    endcase
end

endmodule

proj/CODE/UART/testbench.sv
`timescale 1ns/1ps
module testbench;

parameter m = 8;

logic i_clk;
logic i_Tx_DV;
logic [m-1:0] i_Tx_b;
logic i_enable;
logic i_select;

logic o_Tx_serial;
logic o_Tx_serial_s;
logic o_Tx_active;
logic o_Tx_active_s;
logic o_data_sent;
logic o_data_sent_s;
logic o_ready;
logic o_ready_s;
logic o_data_recieved;
logic o_data_recieved_s;

UART #(.m(m)) model (.i_clk(i_clk), .i_Tx_DV(i_Tx_DV), .i_Tx_b(i_Tx_b), .i_enable(i_enable), .i_select(i_select), .o_Tx_active(o_Tx_active), .o_data_sent(o_data_sent), .o_ready(o_ready), .o_data_recieved(o_data_recieved));
UART_synth synth(.i_clk(i_clk), .i_Tx_DV(i_Tx_DV), .i_Tx_b(i_Tx_b), .i_enable(i_enable), .i_select(i_select), .o_Tx_active(o_Tx_active_s), .o_data_sent(o_data_sent_s), .o_ready(o_ready_s), .o_data_recieved(o_data_Recieved_s));

initial i_clk = 1;
always #1 i_clk = ~i_clk;                 

initial begin 
    $dumpfile("signals.vcd");
    $dumpvars(0, testbench);

    i_Tx_DV = 0;
    i_enable = 0;
    i_select = 0;
    i_Tx_b = 8'b11101011;
    #1

    i_Tx_DV = 1;
    i_enable = 1;
    #1

    i_select = 1;
    #10

    i_Tx_DV = 0;
    #4

    i_enable = 0;
    i_select = 0;
    #1

    i_Tx_DV = 1;
    i_enable = 1;
    #1

    i_select = 1;
    #8

    i_enable = 0;
    #1

    i_Tx_DV = 0;
    i_enable = 0;
    i_select = 0;
    #1

    i_Tx_DV = 1;
    i_enable = 1;
    #1

    i_select = 1;
    #10

    $finish;
end

endmodule

proj/CODE/UART/signals.vcd
$date
	Thu Jan 25 10:42:33 2024
$end
$version
	Icarus Verilog
$end
$timescale
	1ps
$end
$scope module testbench $end
$var wire 1 ! o_ready_s $end
$var wire 1 " o_ready $end
$var wire 1 # o_data_sent_s $end
$var wire 1 $ o_data_sent $end
$var wire 1 % o_data_recieved $end
$var wire 1 & o_data_Recieved_s $end
$var wire 1 ' o_Tx_active_s $end
$var wire 1 ( o_Tx_active $end
$var parameter 32 ) m $end
$var reg 1 * i_Tx_DV $end
$var reg 8 + i_Tx_b [7:0] $end
$var reg 1 , i_clk $end
$var reg 1 - i_enable $end
$var reg 1 . i_select $end
$scope module model $end
$var wire 1 * i_Tx_DV $end
$var wire 8 / i_Tx_b [7:0] $end
$var wire 1 , i_clk $end
$var wire 1 - i_enable $end
$var wire 1 . i_select $end
$var parameter 32 0 CLKS_PER_BIT $end
$var parameter 32 1 m $end
$var reg 3 2 curr_state [2:0] $end
$var reg 1 ( o_Tx_active $end
$var reg 1 3 o_Tx_serial $end
$var reg 1 % o_data_recieved $end
$var reg 1 $ o_data_sent $end
$var reg 1 " o_ready $end
$var reg 8 4 r_Tx_data [7:0] $end
$var reg 3 5 r_bit_index [2:0] $end
$var reg 8 6 r_clock_count [7:0] $end
$upscope $end
$scope module synth $end
$var wire 1 7 _001_ $end
$var wire 1 8 _002_ $end
$var wire 1 9 _003_ $end
$var wire 1 : _004_ $end
$var wire 1 ; _005_ $end
$var wire 1 < _008_ $end
$var wire 1 = _009_ $end
$var wire 1 > _010_ $end
$var wire 1 ? _011_ $end
$var wire 1 @ _012_ $end
$var wire 1 A _013_ $end
$var wire 1 B _014_ $end
$var wire 1 C _015_ $end
$var wire 1 D _016_ $end
$var wire 1 E _017_ $end
$var wire 1 F _018_ $end
$var wire 1 G _019_ $end
$var wire 1 H _020_ $end
$var wire 1 I _021_ $end
$var wire 1 J _022_ $end
$var wire 1 K _023_ $end
$var wire 1 L _024_ $end
$var wire 1 M _025_ $end
$var wire 1 N _026_ $end
$var wire 1 O _027_ $end
$var wire 1 P _028_ $end
$var wire 1 Q _029_ $end
$var wire 1 R _030_ $end
$var wire 1 S _031_ $end
$var wire 1 T _032_ $end
$var wire 1 U _033_ $end
$var wire 1 V _034_ $end
$var wire 1 W _035_ $end
$var wire 1 X _036_ $end
$var wire 1 Y _037_ $end
$var wire 1 Z _038_ $end
$var wire 1 [ _039_ $end
$var wire 1 \ _040_ $end
$var wire 1 ] _041_ $end
$var wire 1 ^ _042_ $end
$var wire 1 _ _043_ $end
$var wire 1 ` _044_ $end
$var wire 1 a _045_ $end
$var wire 1 b _046_ $end
$var wire 1 c _047_ $end
$var wire 1 d _048_ $end
$var wire 1 e _049_ $end
$var wire 1 f _050_ $end
$var wire 1 g _051_ $end
$var wire 1 h _052_ $end
$var wire 1 i _053_ $end
$var wire 1 j _054_ $end
$var wire 1 k _055_ $end
$var wire 1 l _056_ $end
$var wire 1 m _057_ $end
$var wire 1 n _058_ $end
$var wire 1 o _059_ $end
$var wire 1 p _060_ $end
$var wire 1 q _061_ $end
$var wire 1 r _062_ $end
$var wire 1 s _063_ $end
$var wire 1 t _064_ $end
$var wire 1 u _065_ $end
$var wire 1 v _066_ $end
$var wire 1 w _067_ $end
$var wire 1 x _068_ $end
$var wire 1 y _069_ $end
$var wire 1 z _070_ $end
$var wire 1 { _071_ $end
$var wire 1 | _072_ $end
$var wire 1 } _073_ $end
$var wire 1 ~ _074_ $end
$var wire 1 !" _075_ $end
$var wire 1 "" _076_ $end
$var wire 1 #" _077_ $end
$var wire 1 $" _078_ $end
$var wire 1 %" _079_ $end
$var wire 1 &" _080_ $end
$var wire 1 '" _081_ $end
$var wire 1 (" _082_ $end
$var wire 1 )" _083_ $end
$var wire 1 *" _084_ $end
$var wire 1 +" _085_ $end
$var wire 1 ," _086_ $end
$var wire 1 -" _087_ $end
$var wire 1 ." _088_ $end
$var wire 1 /" _089_ $end
$var wire 1 0" _090_ $end
$var wire 1 1" _091_ $end
$var wire 1 2" _092_ $end
$var wire 1 3" _093_ $end
$var wire 1 4" _094_ $end
$var wire 1 * i_Tx_DV $end
$var wire 8 5" i_Tx_b [7:0] $end
$var wire 1 , i_clk $end
$var wire 1 - i_enable $end
$var wire 1 . i_select $end
$var wire 3 6" _007_ [2:0] $end
$var wire 8 7" _006_ [7:0] $end
$var wire 3 8" _000_ [2:0] $end
$var reg 3 9" curr_state [2:0] $end
$var reg 1 ' o_Tx_active $end
$var reg 1 :" o_Tx_serial $end
$var reg 1 & o_data_recieved $end
$var reg 1 # o_data_sent $end
$var reg 1 ! o_ready $end
$var reg 8 ;" r_Tx_data [7:0] $end
$var reg 3 <" r_bit_index [2:0] $end
$upscope $end
$upscope $end
$enddefinitions $end
$comment Show the parameter values. $end
$dumpall
b1000 1
b1 0
b1000 )
$end
#0
$dumpvars
b0 <"
b0 ;"
1:"
b0 9"
b0 8"
b0 7"
b0 6"
b11101011 5"
04"
03"
02"
01"
00"
0/"
0."
0-"
1,"
0+"
0*"
0)"
1("
0'"
0&"
0%"
1$"
0#"
0""
1!"
0~
0}
1|
0{
0z
0y
1x
0w
1v
0u
0t
1s
0r
1q
1p
0o
1n
0m
0l
1k
1j
1i
1h
1g
1f
1e
1d
0c
0b
0a
1`
0_
0^
0]
0\
0[
0Z
0Y
0X
1W
0V
0U
0T
0S
0R
0Q
0P
0O
0N
0M
0L
0K
0J
0I
0H
0G
0F
0E
0D
0C
0B
xA
0@
1?
1>
1=
1<
1;
0:
09
18
x7
b0 6
b0 5
b0 4
13
b0 2
b11101011 /
0.
0-
1,
b11101011 +
0*
x(
x'
0&
0%
0$
0#
1"
x!
$end
#1000
0;
17
b11101011 7"
0p
1A
1B
1D
1H
1L
1N
1P
b1 8"
19
0n
1o
0d
1m
1-
1*
0,
#2000
12"
08
10"
1&"
0B
0D
0H
0L
0N
0P
0?
1C
1E
1I
1M
1O
1Q
1/"
1z
0o
0q
0>
1p
1Y
b10 8"
1)"
1y
0k
1n
1R
1c
1b
1+"
1'"
1w
0f
1l
1@
b11101011 ;"
b1 9"
1&
0!
1'
b1 2
b11101011 4
1(
1%
0"
0=
0<
0`
1%"
0|
1}
14"
1T
1{
1.
1,
#3000
0,
#4000
0R
18
b1 6"
0v
13"
1U
1X
0b
1u
1f
0@
0e
1r
b10 2
03
0:"
b10 9"
1,
#5000
0,
#6000
0&"
0%"
1[
b10 6"
0}
11"
1Z
0U
0j
1*"
0T
b1 <"
1:"
b1 5
13
1,
#7000
0,
#8000
08
03"
1Y
02"
b11 6"
1X
1}
01"
0Z
1U
0$"
0/"
0]
1."
1W
1j
0*"
1T
0i
1~
1-"
0V
b10 5
b10 <"
1,
#9000
0,
#10000
18
0Y
13"
0X
12"
0W
1]
b100 6"
0}
11"
1V
1Z
0U
0j
1*"
0T
1^
b11 <"
0:"
b11 5
03
1,
#11000
0,
#12000
08
1\
03"
1Y
0z
b10 8"
02"
0[
1%"
b101 6"
1X
0y
0a
1}
01"
0Z
1U
1$"
1/"
0]
0."
1W
0x
1#"
0`
1j
0*"
1T
1i
0~
0-"
0V
0^
0h
1""
0_
b100 5
13
1:"
b100 <"
1d
0m
1,
0*
#13000
0,
#14000
18
13"
0%"
12"
1[
b110 6"
0}
11"
1Z
0U
0j
1*"
0T
b101 <"
0:"
b101 5
03
1,
#15000
0,
#16000
0/"
1."
1?
1j
0i
1z
1-"
1=
b11 2
1:"
b110 <"
18
b11 8"
03"
1a
02"
1[
b110 6"
1<
1`
01"
0Z
0U
1|
0*"
04"
0T
0{
1,
0.
0-
#17000
0d
1m
0,
1-
1*
#18000
1\
1R
1Y
07
1v
0X
1>
1:
0s
0u
0f
b11 9"
0(
b100 2
1$
13
03"
1?
b100 8"
12"
0=
0a
1&"
b110 6"
0<
0`
1%"
0U
0|
1}
14"
1T
1{
1,
1.
#19000
0,
#20000
1;
b0 6"
0\
1s
1q
0:
0Y
09
1k
0n
0R
0c
0m
04"
1=
1f
b0 8"
1e
0l
0r
0g
1<
0A
0t
b0 2
b0 5
0$
0%
1"
0'
1#
b100 9"
1,
#21000
0,
#22000
17
1A
1B
1D
1H
1L
1N
1P
b1 8"
19
1y
12"
1o
b11101011 7"
1x
0#"
1/"
1&"
0."
1m
14"
0;
0C
0E
0I
0M
0O
0Q
0=
1h
0""
1i
1z
0-"
0[
1g
0p
0<
b0 <"
b0 9"
0&
1!
0#
b1 2
1(
1%
0"
1,
#23000
0,
#24000
08
0B
0D
0H
0L
0N
0P
0?
1C
1E
1I
1M
1O
1Q
0o
0q
0>
1p
1Y
b10 8"
0k
1n
1R
1c
1b
0f
1l
1@
b10 2
03
1'
0!
1&
b1 9"
1,
#25000
0,
#26000
0R
0v
1X
1a
1u
0e
1r
1f
0@
b10 9"
0:"
b11 2
08
0?
02"
0=
0&"
b11 8"
1<
1`
0%"
0b
1|
0}
04"
0T
0{
1,
0-
#27000
1d
0m
0,
0.
0*
#28000
18
1R
1Y
1?
07
1v
0X
0a
1>
1:
0s
0u
0f
b100 8"
0(
b100 2
1$
13
b11 9"
0d
1m
1,
1-
1*
#29000
12"
1&"
0<
0`
1%"
0|
1}
14"
1T
1{
0,
1.
#30000
1;
1q
0Y
09
0:
1s
0m
04"
1=
1k
0n
0R
0c
0g
1<
1e
0r
1f
0l
b0 8"
0t
0A
b100 9"
1#
1:"
0'
b0 2
0$
0%
1"
1,
#31000
0,
#32000
17
1A
1B
1D
1H
1L
1N
1P
b1 8"
19
1o
b11101011 7"
1m
14"
0;
0C
0E
0I
0M
0O
0Q
0=
1g
0p
0<
b1 2
1(
1%
0"
0#
1!
0&
b0 9"
1,
#33000
0,
#34000
08
0B
0D
0H
0L
0N
0P
0?
1C
1E
1I
1M
1O
1Q
0o
0q
0>
1p
1Y
b10 8"
0k
1n
1R
1c
1b
0f
1l
1@
b1 9"
1&
0!
1'
b10 2
03
1,
#35000
0,
#36000
0R
18
b1 6"
0v
13"
1U
1X
0b
1u
1f
0@
0e
1r
b1 5
13
0:"
b10 9"
1,
#37000
0,
#38000
0&"
0%"
1[
b10 6"
0}
11"
1Z
0U
0j
1*"
0T
b1 <"
1:"
b10 5
1,
