proj/CODE/APB/APBrtl.sv
/* Generated by Yosys 0.9 (git sha1 1979e0b) */

module APBrtl(PCLK, PRESET, PSEL0, PSEL1, PSEL2, PSEL3, PENABLE, PWRITE, PWDATA, PREADY, PRDATA, i_data, i_data_ready, i_alu_error, i_data_check, i_protocol_sel, o_waiting, o_transfer_done);
  wire _00_;
  wire _01_;
  wire _02_;
  wire _03_;
  wire _04_;
  wire _05_;
  wire _06_;
  wire _07_;
  wire _08_;
  wire _09_;
  wire _10_;
  wire _11_;
  wire _12_;
  wire _13_;
  wire _14_;
  wire _15_;
  wire _16_;
  wire _17_;
  wire _18_;
  wire _19_;
  wire _20_;
  wire _21_;
  wire _22_;
  wire _23_;
  wire _24_;
  wire _25_;
  wire _26_;
  wire _27_;
  wire _28_;
  input PCLK;
  output PENABLE;
  input PRDATA;
  input PREADY;
  input PRESET;
  output PSEL0;
  output PSEL1;
  output PSEL2;
  output PSEL3;
  output [7:0] PWDATA;
  output PWRITE;
  reg [2:0] curr_state;
  input i_alu_error;
  input [7:0] i_data;
  input i_data_check;
  input i_data_ready;
  input [1:0] i_protocol_sel;
  output o_transfer_done;
  output o_waiting;
  assign _03_ = ~i_data_ready;
  assign _04_ = ~i_data_check;
  assign _05_ = ~PREADY;
  assign _06_ = ~PRESET;
  assign _07_ = ~i_protocol_sel[1];
  assign _08_ = ~i_protocol_sel[0];
  assign _09_ = _03_ | i_alu_error;
  assign _10_ = ~_09_;
  assign _11_ = PRESET & _10_;
  assign _12_ = _06_ | _09_;
  assign _13_ = _04_ & _12_;
  assign _14_ = i_data_check | _11_;
  assign _15_ = curr_state[0] | curr_state[1];
  assign _16_ = PREADY & PRESET;
  assign _17_ = _15_ & _16_;
  assign _02_ = _14_ & _17_;
  assign _18_ = _05_ | _13_;
  assign _19_ = curr_state[0] & _18_;
  assign _20_ = curr_state[1] & PREADY;
  assign _21_ = _04_ & _20_;
  assign _22_ = _09_ & _21_;
  assign _23_ = _06_ | _22_;
  assign _00_ = _19_ | _23_;
  assign _24_ = curr_state[1] & _05_;
  assign _25_ = curr_state[2] | _24_;
  assign _01_ = PRESET & _25_;
  assign _26_ = _04_ & curr_state[2];
  assign PWDATA[0] = i_data[0] & _26_;
  assign PWDATA[1] = i_data[1] & _26_;
  assign PWDATA[2] = i_data[2] & _26_;
  assign PWDATA[3] = i_data[3] & _26_;
  assign PWDATA[4] = i_data[4] & _26_;
  assign PWDATA[5] = i_data[5] & _26_;
  assign PWDATA[6] = i_data[6] & _26_;
  assign PWDATA[7] = i_data[7] & _26_;
  assign PWRITE = curr_state[0] | _26_;
  assign o_waiting = curr_state[0] & _16_;
  assign _27_ = curr_state[2] & i_protocol_sel[1];
  assign PSEL3 = i_protocol_sel[0] & _27_;
  assign PSEL2 = _08_ & _27_;
  assign _28_ = curr_state[2] & _07_;
  assign PSEL1 = i_protocol_sel[0] & _28_;
  assign PSEL0 = _08_ & _28_;
  always @(posedge PCLK)
      curr_state[0] <= _00_;
  always @(posedge PCLK)
      curr_state[1] <= _01_;
  always @(posedge PCLK)
      curr_state[2] <= _02_;
  assign PENABLE = curr_state[1];
  assign o_transfer_done = 1'h0;
endmodule

proj/CODE/APB/APB_defines.vh
`ifndef APB_DEFINES
`define APB_DEFINES

`define INACTIVE    2'b00
`define SETUP   	2'b01
`define ACTIVE  	2'b10

`define WRITE   	1'b1
`define READ    	1'b0

`endif

proj/CODE/APB/APB.sv
`include "APB_defines.vh"

module APB (
    PCLK, PRESET, PSEL0, PSEL1, PSEL2, PSEL3, 
    PENABLE, PWRITE, PWDATA, PREADY, PRDATA, 
    i_data, i_data_ready, i_alu_error, i_data_check, 
    i_protocol_sel, o_waiting, o_transfer_done
);

parameter m = 8;

input logic PCLK;
input logic PRESET;
input logic PREADY;
input logic PRDATA;
input logic [m-1:0] i_data;
input logic i_data_ready;
input logic i_alu_error;
input logic [1:0] i_protocol_sel;
input logic i_data_check;

output logic PSEL0;
output logic PSEL1;
output logic PSEL2;
output logic PSEL3;
output logic PENABLE;
output logic PWRITE;
output logic [m-1:0] PWDATA;
output logic o_waiting;
output logic o_transfer_done;

reg [1:0] curr_state;
reg [1:0] next_state;
reg fb_check;
reg fb;

    

always @(curr_state or PRESET or PREADY 
		 or PRDATA or i_data or i_data_ready 
		 or i_alu_error or i_protocol_sel 
		 or i_data_check) 
	begin
    
	PSEL0 = 0;
    PSEL1 = 0;
    PSEL2 = 0;
    PSEL3 = 0;
    PENABLE = 0;
    PWRITE = 0;
    PWDATA = 0;
    o_waiting = 0;
    o_transfer_done = 0;
    fb_check = 1;
	fb = 0;
    //i_data_check = 0;
    //i_protocol_sel = 0;


    case (curr_state)
    
        `INACTIVE: begin
        
            PSEL0 = 0;
            PSEL1 = 0;
            PSEL2 = 0;
            PSEL3 = 0;
            PENABLE = 0;
            PWDATA = 0;
            PWRITE = `WRITE;
            o_transfer_done = fb;
            
            if (i_alu_error & PRESET & PREADY & fb_check) begin
                o_waiting = 1;
                o_transfer_done = 0;
            end
            
            else if (PRESET == 0) begin
                o_waiting = 0;
                o_transfer_done = 0;
            end
            
            else if (PRESET & PREADY & fb_check) o_waiting = 1;
            if (((i_data_ready & ~i_alu_error & o_waiting)|i_data_check) & PREADY) next_state = `SETUP;
            else next_state = `INACTIVE;
        end
        
        `SETUP: begin
        
            PENABLE = 0;
            o_waiting = 0;
            o_transfer_done = 0;
            
            if (i_data_check) begin
                PWRITE = `READ;
                PWDATA = 0;
                fb_check = 1;
            end
            
            else begin
                PWRITE = `WRITE;
                PWDATA = i_data;
                fb_check = 0;
            end
            
            case (i_protocol_sel)
                2'b00: begin
                    PSEL0 = 1;
                    PSEL1 = 0;
                    PSEL2 = 0;
                    PSEL3 = 0;
                end
                
                2'b01: begin
                    PSEL0 = 0;
                    PSEL1 = 1;
                    PSEL2 = 0;
                    PSEL3 = 0;
                end
                
                2'b10: begin
                    PSEL0 = 0;
                    PSEL1 = 0;
                    PSEL2 = 1;
                    PSEL3 = 0;
                end
                
                2'b11: begin
                    PSEL0 = 0;
                    PSEL1 = 0;
                    PSEL2 = 0;
                    PSEL3 = 1;
                end
                
            endcase
            
            next_state = `ACTIVE;
            
        end
        
        `ACTIVE: begin
        
            PENABLE = 1;
            fb = PRDATA;
            if (PREADY & ((i_data_ready & ~i_alu_error)|i_data_check)) next_state = `SETUP;
            else if (PREADY) next_state = `INACTIVE;
            else next_state = `ACTIVE;
        end
        
        default: next_state = `INACTIVE;
        
    endcase
    
end

always @(posedge PCLK) begin

    if (PRESET == 0) begin
        curr_state = `INACTIVE;
    end
    
    else begin
        curr_state = next_state;
    end
    
end

endmodule

proj/CODE/APB/APBtb.sv
`timescale 1ns/1ps

module APBtb;

parameter m = 8;

logic PCLK;
logic PRESET;
logic PREADY;
logic PRDATA;
logic [m-1:0] i_data;
logic i_data_ready;
logic i_alu_error;
logic [1:0] i_protocol_sel;
logic i_data_check;

reg PSEL0;
reg PSEL1;
reg PSEL2;
reg PSEL3;
reg PENABLE;
reg PWRITE;
reg [m-1:0] PWDATA;
reg o_waiting;
reg o_transfer_done;

reg PSEL0_synth;
reg PSEL1_synth;
reg PSEL2_synth;
reg PSEL3_synth;
reg PENABLE_synth;
reg PWRITE_synth;
reg [m-1:0] PWDATA_synth;
reg o_waiting_synth;
reg o_transfer_done_synth;

APB #(.m(m))   
		model    		
				(.PCLK(PCLK), 
				 .PRESET(PRESET),
				 .PREADY(PREADY), 
				 .PRDATA(PRDATA), 
				 .i_data_check(i_data_check), 
				 .i_data(i_data), 
				 .i_data_ready(i_data_ready), 
				 .i_alu_error(i_alu_error), 
				 .i_protocol_sel(i_protocol_sel), 
				 .PSEL0(PSEL0), .PSEL1(PSEL1), 
				 .PSEL2(PSEL2), .PSEL3(PSEL3), 
				 .PENABLE(PENABLE), .PWRITE(PWRITE), 
				 .PWDATA(PWDATA), .o_waiting(o_waiting), 
				 .o_transfer_done(o_transfer_done)
				 );
				 
APBrtl                              
		synth    		
				(.PCLK(PCLK), 
				 .PRESET(PRESET), 
				 .PREADY(PREADY), 
				 .PRDATA(PRDATA), 
				 .i_data_check(i_data_check), 
				 .i_data(i_data), 
				 .i_data_ready(i_data_ready), 
				 .i_alu_error(i_alu_error), 
				 .i_protocol_sel(i_protocol_sel), 
				 .PSEL0(PSEL0_synth), .PSEL1(PSEL1_synth), 
				 .PSEL2(PSEL2_synth), .PSEL3(PSEL3_synth), 
				 .PENABLE(PENABLE_synth), .PWRITE(PWRITE_synth), 
				 .PWDATA(PWDATA_synth), .o_waiting(o_waiting_synth), 
				 .o_transfer_done(o_transfer_done_synth)
				 );


initial PCLK = 0;
always #1 PCLK = ~PCLK;                 

initial begin 

    $dumpfile("signals.vcd"); 
    $dumpvars(0,APBtb); 

    PRESET = 0;
    PREADY = 0;
    PRDATA = 0;
    
    i_data = 8'b11110011;
    i_data_ready = 0;
    i_alu_error = 0;
    i_protocol_sel = 0;
    i_data_check = 0;
    
    #3
    PRESET = 1;
    #1
    PREADY = 1;
    #2
    i_data_ready = 1;
    #4
    PREADY = 0;
    i_data_ready = 0;
    #2
    PREADY = 1;
    #4
    i_data_check = 1;
    PRDATA = 1;
    #4
    PREADY = 0;
    #1
    i_data_check = 0;
    #3
    PREADY = 1;
    #2
    PRDATA = 0;
    #4
    
    $finish;
    
end

endmodule

proj/CODE/APB/signals.vcd
$date
	Wed Jan 24 19:01:49 2024
$end
$version
	Icarus Verilog
$end
$timescale
	1ps
$end
$scope module APBtb $end
$var wire 1 ! o_transfer_done_synth $end
$var wire 1 " o_waiting_synth $end
$var wire 1 # o_waiting $end
$var wire 1 $ o_transfer_done $end
$var wire 1 % PWRITE_synth $end
$var wire 1 & PWRITE $end
$var wire 8 ' PWDATA_synth [7:0] $end
$var wire 8 ( PWDATA [7:0] $end
$var wire 1 ) PSEL3_synth $end
$var wire 1 * PSEL3 $end
$var wire 1 + PSEL2_synth $end
$var wire 1 , PSEL2 $end
$var wire 1 - PSEL1_synth $end
$var wire 1 . PSEL1 $end
$var wire 1 / PSEL0_synth $end
$var wire 1 0 PSEL0 $end
$var wire 1 1 PENABLE_synth $end
$var wire 1 2 PENABLE $end
$var reg 1 3 PCLK $end
$var reg 1 4 PRDATA $end
$var reg 1 5 PREADY $end
$var reg 1 6 PRESET $end
$var reg 1 7 i_alu_error $end
$var reg 8 8 i_data [7:0] $end
$var reg 1 9 i_data_check $end
$var reg 1 : i_data_ready $end
$var reg 2 ; i_protocol_sel [1:0] $end
$scope module model $end
$var wire 1 3 PCLK $end
$var wire 1 4 PRDATA $end
$var wire 1 5 PREADY $end
$var wire 1 6 PRESET $end
$var wire 1 7 i_alu_error $end
$var wire 8 < i_data [7:0] $end
$var wire 1 9 i_data_check $end
$var wire 1 : i_data_ready $end
$var wire 2 = i_protocol_sel [1:0] $end
$var reg 1 2 PENABLE $end
$var reg 1 0 PSEL0 $end
$var reg 1 . PSEL1 $end
$var reg 1 , PSEL2 $end
$var reg 1 * PSEL3 $end
$var reg 8 > PWDATA [7:0] $end
$var reg 1 & PWRITE $end
$var reg 2 ? curr_state [1:0] $end
$var reg 1 @ fb $end
$var reg 1 A fb_check $end
$var reg 2 B next_state [1:0] $end
$var reg 1 $ o_transfer_done $end
$var reg 1 # o_waiting $end
$upscope $end
$scope module synth $end
$var wire 1 3 PCLK $end
$var wire 1 4 PRDATA $end
$var wire 1 5 PREADY $end
$var wire 1 6 PRESET $end
$var wire 1 / PSEL0 $end
$var wire 1 - PSEL1 $end
$var wire 1 + PSEL2 $end
$var wire 1 ) PSEL3 $end
$var wire 1 % PWRITE $end
$var wire 1 C _00_ $end
$var wire 1 D _01_ $end
$var wire 1 E _02_ $end
$var wire 1 F _03_ $end
$var wire 1 G _04_ $end
$var wire 1 H _05_ $end
$var wire 1 I _06_ $end
$var wire 1 J _07_ $end
$var wire 1 K _08_ $end
$var wire 1 L _09_ $end
$var wire 1 M _10_ $end
$var wire 1 N _11_ $end
$var wire 1 O _12_ $end
$var wire 1 P _13_ $end
$var wire 1 Q _14_ $end
$var wire 1 R _15_ $end
$var wire 1 S _16_ $end
$var wire 1 T _17_ $end
$var wire 1 U _18_ $end
$var wire 1 V _19_ $end
$var wire 1 W _20_ $end
$var wire 1 X _21_ $end
$var wire 1 Y _22_ $end
$var wire 1 Z _23_ $end
$var wire 1 [ _24_ $end
$var wire 1 \ _25_ $end
$var wire 1 ] _26_ $end
$var wire 1 ^ _27_ $end
$var wire 1 _ _28_ $end
$var wire 1 7 i_alu_error $end
$var wire 8 ` i_data [7:0] $end
$var wire 1 9 i_data_check $end
$var wire 1 : i_data_ready $end
$var wire 2 a i_protocol_sel [1:0] $end
$var wire 1 ! o_transfer_done $end
$var wire 1 " o_waiting $end
$var wire 8 b PWDATA [7:0] $end
$var wire 1 1 PENABLE $end
$var reg 3 c curr_state [2:0] $end
$upscope $end
$upscope $end
$enddefinitions $end
#0
$dumpvars
bx c
bx00xx b
b0 a
b11110011 `
x_
0^
x]
x\
x[
1Z
0Y
0X
0W
xV
1U
0T
0S
xR
0Q
1P
1O
0N
0M
1L
1K
1J
1I
1H
1G
1F
0E
0D
1C
b0 B
1A
0@
bx ?
b0 >
b0 =
b11110011 <
b0 ;
0:
09
b11110011 8
07
06
05
04
03
02
x1
00
x/
0.
0-
0,
0+
0*
0)
b0 (
bx00xx '
0&
x%
0$
0#
0"
0!
$end
#1000
0\
b0 '
b0 b
0/
1V
1%
1R
0[
0]
0_
01
b1 c
1&
b0 ?
13
#2000
03
#3000
0Z
1&
0I
13
16
#4000
1T
1"
1#
1&
0H
1S
03
15
#5000
13
#6000
0C
1E
0V
1Q
0U
1N
0P
1M
0O
0L
b1 B
1#
1&
0F
03
1:
#7000
0E
1D
b11110011 '
b11110011 b
1/
0T
1\
1]
1_
0R
1%
0"
b100 c
b10 B
10
0A
b11110011 (
b11110011 >
0#
1&
b1 ?
13
#8000
03
#9000
1E
1T
1X
0D
b0 '
b0 b
0%
0/
1R
1W
0\
0]
0_
11
b10 c
b1 B
12
1A
b0 (
b0 >
0&
00
b10 ?
13
#10000
0Q
0N
1P
1D
0M
1O
1\
0E
1L
1U
1[
0T
0X
1F
b10 B
12
1H
0S
0W
03
0:
05
#11000
13
#12000
1C
0D
1Z
0\
1Y
0[
1T
1X
b0 B
12
0H
1S
1W
03
15
#13000
0Z
0Y
0X
1V
1%
1"
0W
01
b1 c
1#
1&
02
b0 ?
13
#14000
03
#15000
13
#16000
0C
0V
0U
0P
1E
b1 B
1#
1&
0G
1Q
03
14
19
#17000
0E
0T
1D
1/
0R
0%
0"
1\
1_
b100 c
b10 B
10
0#
0&
b1 ?
13
#18000
03
#19000
1E
0D
0/
1T
0\
0_
1R
1W
11
b10 c
b1 B
1@
12
00
b10 ?
13
#20000
1D
1\
0E
1U
1[
0T
b10 B
1@
12
1H
0S
0W
03
05
#21000
1P
1@
12
1G
0Q
13
09
#22000
03
#23000
13
#24000
1C
0D
1Z
0\
1Y
0[
1T
1X
b0 B
1@
12
0H
1S
1W
03
15
#25000
0Z
0Y
0X
1V
1%
1"
0W
01
b1 c
1#
1&
0@
02
b0 ?
13
#26000
1#
1&
03
04
